[
  {
    "bbox": [
      39,
      175,
      321,
      201
    ],
    "text": "SIMPLIFIED TAX INVOICE",
    "class": "TAX",
    "class_id": 4
  },
  {
    "bbox": [
      41,
      199,
      317,
      223
    ],
    "text": "AA PHARMACY",
    "class": "ITEM",
    "class_id": 5
  },
  {
    "bbox": [
      42,
      223,
      312,
      248
    ],
    "text": "SUBANG HEALTHCARE SDN",
    "class": "COMPANY",
    "class_id": 0
  },
  {
    "bbox": [
      41,
      248,
      162,
      274
    ],
    "text": "1118258-K",
    "class": "DOCUMENT_NO",
    "class_id": 9
  },
  {
    "bbox": [
      39,
      274,
      297,
      299
    ],
    "text": "GST NO: 001536708608",
    "class": "TAX",
    "class_id": 4
  },
  {
    "bbox": [
      42,
      300,
      284,
      326
    ],
    "text": "B-8, JALAN SS15/4D,",
    "class": "OTHER",
    "class_id": 11
  },
  {
    "bbox": [
      42,
      325,
      384,
      350
    ],
    "text": "47500 SUBANG JAYA, SELANGOR",
    "class": "ADDRESS",
    "class_id": 1
  },
  {
    "bbox": [
      43,
      348,
      249,
      373
    ],
    "text": "TEL: 03-56127718",
    "class": "DOCUMENT_NO",
    "class_id": 9
  },
  {
    "bbox": [
      41,
      398,
      98,
      423
    ],
    "text": "CASH",
    "class": "OTHER",
    "class_id": 11
  },
  {
    "bbox": [
      42,
      450,
      310,
      473
    ],
    "text": "RECEIPT #: CS00251915",
    "class": "DOCUMENT_NO",
    "class_id": 9
  },
  {
    "bbox": [
      318,
      448,
      520,
      474
    ],
    "text": "DATE: 29/10/2017",
    "class": "DATE",
    "class_id": 2
  },
  {
    "bbox": [
      43,
      473,
      246,
      499
    ],
    "text": "SALESPERSON : C3",
    "class": "ITEM",
    "class_id": 5
  },
  {
    "bbox": [
      317,
      473,
      497,
      499
    ],
    "text": "TIME: 20:18:00",
    "class": "OTHER",
    "class_id": 11
  },
  {
    "bbox": [
      41,
      499,
      197,
      524
    ],
    "text": "CASHIER : C3",
    "class": "CASHIER",
    "class_id": 10
  },
  {
    "bbox": [
      44,
      547,
      98,
      574
    ],
    "text": "ITEM",
    "class": "OTHER",
    "class_id": 11
  },
  {
    "bbox": [
      266,
      548,
      308,
      575
    ],
    "text": "QTY",
    "class": "OTHER",
    "class_id": 11
  },
  {
    "bbox": [
      365,
      548,
      408,
      574
    ],
    "text": "U/P",
    "class": "OTHER",
    "class_id": 11
  },
  {
    "bbox": [
      442,
      547,
      522,
      572
    ],
    "text": "AMOUNT",
    "class": "ITEM",
    "class_id": 5
  },
  {
    "bbox": [
      341,
      574,
      409,
      606
    ],
    "text": "(GST)",
    "class": "TAX",
    "class_id": 4
  },
  {
    "bbox": [
      457,
      574,
      518,
      606
    ],
    "text": "(GST)",
    "class": "TAX",
    "class_id": 4
  },
  {
    "bbox": [
      44,
      622,
      124,
      650
    ],
    "text": "030249",
    "class": "QTY",
    "class_id": 6
  },
  {
    "bbox": [
      267,
      628,
      283,
      650
    ],
    "text": "1",
    "class": "QTY",
    "class_id": 6
  },
  {
    "bbox": [
      344,
      627,
      409,
      649
    ],
    "text": "14.90",
    "class": "LINE_TOTAL",
    "class_id": 8
  },
  {
    "bbox": [
      454,
      625,
      548,
      649
    ],
    "text": "14.90 S",
    "class": "OTHER",
    "class_id": 11
  },
  {
    "bbox": [
      46,
      651,
      546,
      676
    ],
    "text": "(BOX 100S) SUPER SAFE POWDER FREE NITRIL",
    "class": "ITEM",
    "class_id": 5
  },
  {
    "bbox": [
      42,
      676,
      105,
      700
    ],
    "text": "03022",
    "class": "QTY",
    "class_id": 6
  },
  {
    "bbox": [
      267,
      679,
      281,
      700
    ],
    "text": "1",
    "class": "QTY",
    "class_id": 6
  },
  {
    "bbox": [
      344,
      676,
      407,
      702
    ],
    "text": "14.00",
    "class": "LINE_TOTAL",
    "class_id": 8
  },
  {
    "bbox": [
      456,
      676,
      545,
      702
    ],
    "text": "14.00 S",
    "class": "OTHER",
    "class_id": 11
  },
  {
    "bbox": [
      43,
      702,
      547,
      730
    ],
    "text": "(S SIZE) SUPER SAFE LATEX GLOVE POWDER F",
    "class": "ITEM",
    "class_id": 5
  },
  {
    "bbox": [
      44,
      752,
      227,
      777
    ],
    "text": "TOTAL QUANTITY",
    "class": "OTHER",
    "class_id": 11
  },
  {
    "bbox": [
      354,
      752,
      372,
      776
    ],
    "text": "2",
    "class": "QTY",
    "class_id": 6
  },
  {
    "bbox": [
      304,
      825,
      420,
      853
    ],
    "text": "SUB-TOTAL",
    "class": "OTHER",
    "class_id": 11
  },
  {
    "bbox": [
      480,
      827,
      548,
      851
    ],
    "text": "27.27",
    "class": "LINE_TOTAL",
    "class_id": 8
  },
  {
    "bbox": [
      303,
      852,
      357,
      877
    ],
    "text": "DISC",
    "class": "OTHER",
    "class_id": 11
  },
  {
    "bbox": [
      491,
      853,
      548,
      877
    ],
    "text": "0.00",
    "class": "LINE_TOTAL",
    "class_id": 8
  },
  {
    "bbox": [
      305,
      879,
      346,
      902
    ],
    "text": "GST",
    "class": "TAX",
    "class_id": 4
  },
  {
    "bbox": [
      491,
      879,
      544,
      901
    ],
    "text": "1.64",
    "class": "LINE_TOTAL",
    "class_id": 8
  },
  {
    "bbox": [
      305,
      903,
      408,
      929
    ],
    "text": "ROUNDING",
    "class": "ITEM",
    "class_id": 5
  },
  {
    "bbox": [
      482,
      905,
      543,
      929
    ],
    "text": "-0.01",
    "class": "LINE_TOTAL",
    "class_id": 8
  },
  {
    "bbox": [
      69,
      923,
      194,
      954
    ],
    "text": "TOTAL",
    "class": "OTHER",
    "class_id": 11
  },
  {
    "bbox": [
      415,
      927,
      544,
      953
    ],
    "text": "28.90",
    "class": "TOTAL",
    "class_id": 3
  },
  {
    "bbox": [
      67,
      953,
      169,
      977
    ],
    "text": "CASH",
    "class": "OTHER",
    "class_id": 11
  },
  {
    "bbox": [
      415,
      953,
      542,
      978
    ],
    "text": "28.90",
    "class": "LINE_TOTAL",
    "class_id": 8
  },
  {
    "bbox": [
      68,
      978,
      221,
      1004
    ],
    "text": "CHANGE",
    "class": "ITEM",
    "class_id": 5
  },
  {
    "bbox": [
      441,
      977,
      545,
      1003
    ],
    "text": "0.00",
    "class": "LINE_TOTAL",
    "class_id": 8
  },
  {
    "bbox": [
      106,
      1078,
      481,
      1107
    ],
    "text": "GOODS SOLD ARE NOT RETURNABLE,",
    "class": "ITEM",
    "class_id": 5
  },
  {
    "bbox": [
      230,
      1105,
      360,
      1129
    ],
    "text": "THANK YOU.",
    "class": "ITEM",
    "class_id": 5
  },
  {
    "bbox": [
      105,
      1131,
      483,
      1161
    ],
    "text": "S=STANDARD RATED, Z=ZERO RATED",
    "class": "ITEM",
    "class_id": 5
  },
  {
    "bbox": [
      40,
      1231,
      186,
      1259
    ],
    "text": "GST SUMMARY",
    "class": "TAX",
    "class_id": 4
  },
  {
    "bbox": [
      42,
      1282,
      97,
      1308
    ],
    "text": "CODE",
    "class": "OTHER",
    "class_id": 11
  },
  {
    "bbox": [
      243,
      1282,
      316,
      1307
    ],
    "text": "AMOUNT",
    "class": "ITEM",
    "class_id": 5
  },
  {
    "bbox": [
      374,
      1285,
      396,
      1311
    ],
    "text": "%",
    "class": "OTHER",
    "class_id": 11
  },
  {
    "bbox": [
      443,
      1283,
      531,
      1309
    ],
    "text": "TAX/AMT",
    "class": "TAX",
    "class_id": 4
  },
  {
    "bbox": [
      41,
      1334,
      73,
      1360
    ],
    "text": "SR",
    "class": "OTHER",
    "class_id": 11
  },
  {
    "bbox": [
      257,
      1334,
      324,
      1359
    ],
    "text": "27.27",
    "class": "LINE_TOTAL",
    "class_id": 8
  },
  {
    "bbox": [
      378,
      1335,
      396,
      1361
    ],
    "text": "6",
    "class": "QTY",
    "class_id": 6
  },
  {
    "bbox": [
      479,
      1334,
      533,
      1359
    ],
    "text": "1.64",
    "class": "LINE_TOTAL",
    "class_id": 8
  },
  {
    "bbox": [
      280,
      1411,
      407,
      1436
    ],
    "text": "TAX TOTAL:",
    "class": "TAX",
    "class_id": 4
  },
  {
    "bbox": [
      479,
      1410,
      538,
      1436
    ],
    "text": "1.64",
    "class": "LINE_TOTAL",
    "class_id": 8
  },
  {
    "bbox": [
      329,
      224,
      371,
      249
    ],
    "text": "BHD",
    "class": "OTHER",
    "class_id": 11
  }
]